elephantblog/__init__.py
elephantblog/admin.py
elephantblog/contents.py
elephantblog/feeds.py
elephantblog/modeladmins.py
elephantblog/models.py
elephantblog/sitemap.py
elephantblog/tests.py
elephantblog/transforms.py
elephantblog/urls.py
elephantblog/utils.py
elephantblog/views.py
elephantblog/extensions/__init__.py
elephantblog/extensions/sites.py
elephantblog/extensions/tags.py
elephantblog/locale/cs/LC_MESSAGES/django.mo
elephantblog/locale/cs/LC_MESSAGES/django.po
elephantblog/locale/de/LC_MESSAGES/django.mo
elephantblog/locale/de/LC_MESSAGES/django.po
elephantblog/locale/fr/LC_MESSAGES/django.mo
elephantblog/locale/fr/LC_MESSAGES/django.po
elephantblog/locale/ru/LC_MESSAGES/django.mo
elephantblog/locale/ru/LC_MESSAGES/django.po
elephantblog/management/__init__.py
elephantblog/management/commands/__init__.py
elephantblog/navigation_extensions/__init__.py
elephantblog/navigation_extensions/common.py
elephantblog/navigation_extensions/recursetree.py
elephantblog/navigation_extensions/treeinfo.py
elephantblog/templates/admin/feincms/elephantblog/entry/item_editor.html
elephantblog/templates/content/elephantblog/category_list.html
elephantblog/templates/content/elephantblog/entry_list.html
elephantblog/templates/elephantblog/entry_archive.html
elephantblog/templates/elephantblog/entry_description.html
elephantblog/templates/elephantblog/entry_detail.html
elephantblog/templatetags/__init__.py
elephantblog/templatetags/blog_widgets.py
elephantblog/templatetags/elephantblog_tags.py
feincms_elephantblog-22.0.0.dist-info/LICENSE
feincms_elephantblog-22.0.0.dist-info/METADATA
feincms_elephantblog-22.0.0.dist-info/WHEEL
feincms_elephantblog-22.0.0.dist-info/top_level.txt
feincms_elephantblog-22.0.0.dist-info/RECORD
